fdp_msg_check/__init__.py
fdp_msg_check/main.py
fdp_msg_check/msg_check.py
fdp_msg_check/utils.py
fdp_msg_check-0.0.3.dist-info/METADATA
fdp_msg_check-0.0.3.dist-info/WHEEL
fdp_msg_check-0.0.3.dist-info/entry_points.txt
fdp_msg_check-0.0.3.dist-info/top_level.txt
fdp_msg_check-0.0.3.dist-info/RECORD
