Metadata-Version: 2.1
Name: fdp-msg-check
Version: 0.0.3
Summary: A tool for fix message checking for FDP
Author: tangjicheng
Author-email: tangjch15@gmail.com
Requires-Dist: loguru
